Workbook

Sheet PEDIDOS_CLIENTES AUTOMATICO
A10: Data | B10: =TODAY() -> 46110 | G10: ORDEM DE COMPRA CLIENTE
H12: CÓDIGO LUBEFER ( DIGITAR AQUI )
A13: Cliente | B13: =IFERROR(IF($H$13="","",VLOOKUP($H$13,BANCO_DADOS_CLIENTES!A:L,2,0)),"-") | F13: Código do Cliente
A15: Endereço | B15: =IFERROR(IF($H$13="","",VLOOKUP($H$13,BANCO_DADOS_CLIENTES!A:L,3,0)),"-") | E15: Bairro | F15: =IFERROR(IF($H$13="","",VLOOKUP($H$13,BANCO_DADOS_CLIENTES!A:L,5,0)),"-") | H15: Fone | I15: =IFERROR(IF($H$13="","",VLOOKUP($H$13,BANCO_DADOS_CLIENTES!A:L,9,0)),"-")
A17: CNPJ | B17: =IFERROR(IF($H$13="","",VLOOKUP($H$13,BANCO_DADOS_CLIENTES!A:L,8,0)),"-") | D17: Vendedor | E17: =IFERROR(IF($H$13="","",VLOOKUP($H$13,BANCO_DADOS_CLIENTES!A:M,12,0)),"-") | G17: Email | H17: =IFERROR(IF($H$13="","",VLOOKUP($H$13,BANCO_DADOS_CLIENTES!A:L,10,0)),"-")
A20: INSCRIÇÃO ESTADUAL | B20: =IFERROR(IF($H$13="","",VLOOKUP($H$13,BANCO_DADOS_CLIENTES!A:M,13,0)),"-") | E20: Comprador
A22: Cidade | B22: =IFERROR(IF($H$13="","",VLOOKUP($H$13,BANCO_DADOS_CLIENTES!A:L,6,0)),"-") | E22: Estado | F22: =IFERROR(IF($H$13="","",VLOOKUP($H$13,BANCO_DADOS_CLIENTES!A:L,7,0)),"-")
A24: Condições Pagto | G24: ATUALIZAÇÕES | H24: PREÇO BAIXO É BOM, MAS COM QUALIDADE É MELHOR! LUBEFER
C25: N° DE PARCELAS VALORES APROXIMADOS | E25: =IFERROR(H73/D25,"")
A27: Transporte
A29: QUANT. | B29: CÓDIGO LUBEFER | C29: DESCRIÇÃO | G29: NCM CÓDIGO DE BARRA | H29: PREÇO UNITÁRIO | I29: TOTAL | J29: DESCONTO | K29: ENCARTELADO BSP ESPECIAL | L29: IPI | M29: ST
C32: =IFERROR(VLOOKUP(B32,BANCO_DADOS_PEÇAS!B:C,2,0),"") | G32: =IFERROR(VLOOKUP(B32,BANCO_DADOS_PEÇAS!B:H,6,0),"") | H32: =IFERROR(VLOOKUP(B32,BANCO_DADOS_PEÇAS!B:D,3,0)*(100%+K32)*(100%-J32),"") | I32: =IFERROR((IFERROR(H32+(H32*L32)+(H32*M32),H32)*A32),0) -> 0 | L32: =IFERROR(VLOOKUP(B32,BANCO_DADOS_PEÇAS!B:H,7,0),0)/100 -> 0
C33: =IFERROR(VLOOKUP(B33,BANCO_DADOS_PEÇAS!B:C,2,0),"") | G33: =IFERROR(VLOOKUP(B33,BANCO_DADOS_PEÇAS!B:H,6,0),"") | H33: =IFERROR(VLOOKUP(B33,BANCO_DADOS_PEÇAS!B:D,3,0)*(100%+K33)*(100%-J33),"") | I33: =IFERROR((IFERROR(H33+(H33*L33)+(H33*M33),H33)*A33),0) -> 0 | L33: =IFERROR(VLOOKUP(B33,BANCO_DADOS_PEÇAS!B:H,7,0),0)/100 -> 0
C34: =IFERROR(VLOOKUP(B34,BANCO_DADOS_PEÇAS!B:C,2,0),"") | G34: =IFERROR(VLOOKUP(B34,BANCO_DADOS_PEÇAS!B:H,6,0),"") | H34: =IFERROR(VLOOKUP(B34,BANCO_DADOS_PEÇAS!B:D,3,0)*(100%+K34)*(100%-J34),"") | I34: =IFERROR((IFERROR(H34+(H34*L34)+(H34*M34),H34)*A34),0) -> 0 | L34: =IFERROR(VLOOKUP(B34,BANCO_DADOS_PEÇAS!B:H,7,0),0)/100 -> 0
C35: =IFERROR(VLOOKUP(B35,BANCO_DADOS_PEÇAS!B:C,2,0),"") | G35: =IFERROR(VLOOKUP(B35,BANCO_DADOS_PEÇAS!B:H,6,0),"") | H35: =IFERROR(VLOOKUP(B35,BANCO_DADOS_PEÇAS!B:D,3,0)*(100%+K35)*(100%-J35),"") | I35: =IFERROR((IFERROR(H35+(H35*L35)+(H35*M35),H35)*A35),0) -> 0 | L35: =IFERROR(VLOOKUP(B35,BANCO_DADOS_PEÇAS!B:H,7,0),0)/100 -> 0
C36: =IFERROR(VLOOKUP(B36,BANCO_DADOS_PEÇAS!B:C,2,0),"") | G36: =IFERROR(VLOOKUP(B36,BANCO_DADOS_PEÇAS!B:H,6,0),"") | H36: =IFERROR(VLOOKUP(B36,BANCO_DADOS_PEÇAS!B:D,3,0)*(100%+K36)*(100%-J36),"") | I36: =IFERROR((IFERROR(H36+(H36*L36)+(H36*M36),H36)*A36),0) -> 0 | L36: =IFERROR(VLOOKUP(B36,BANCO_DADOS_PEÇAS!B:H,7,0),0)/100 -> 0
C37: =IFERROR(VLOOKUP(B37,BANCO_DADOS_PEÇAS!B:C,2,0),"") | G37: =IFERROR(VLOOKUP(B37,BANCO_DADOS_PEÇAS!B:H,6,0),"") | H37: =IFERROR(VLOOKUP(B37,BANCO_DADOS_PEÇAS!B:D,3,0)*(100%+K37)*(100%-J37),"") | I37: =IFERROR((IFERROR(H37+(H37*L37)+(H37*M37),H37)*A37),0) -> 0 | L37: =IFERROR(VLOOKUP(B37,BANCO_DADOS_PEÇAS!B:H,7,0),0)/100 -> 0
C38: =IFERROR(VLOOKUP(B38,BANCO_DADOS_PEÇAS!B:C,2,0),"") | G38: =IFERROR(VLOOKUP(B38,BANCO_DADOS_PEÇAS!B:H,6,0),"") | H38: =IFERROR(VLOOKUP(B38,BANCO_DADOS_PEÇAS!B:D,3,0)*(100%+K38)*(100%-J38),"") | I38: =IFERROR((IFERROR(H38+(H38*L38)+(H38*M38),H38)*A38),0) -> 0 | L38: =IFERROR(VLOOKUP(B38,BANCO_DADOS_PEÇAS!B:H,7,0),0)/100 -> 0
C39: =IFERROR(VLOOKUP(B39,BANCO_DADOS_PEÇAS!B:C,2,0),"") | G39: =IFERROR(VLOOKUP(B39,BANCO_DADOS_PEÇAS!B:H,6,0),"") | H39: =IFERROR(VLOOKUP(B39,BANCO_DADOS_PEÇAS!B:D,3,0)*(100%+K39)*(100%-J39),"") | I39: =IFERROR((IFERROR(H39+(H39*L39)+(H39*M39),H39)*A39),0) -> 0 | L39: =IFERROR(VLOOKUP(B39,BANCO_DADOS_PEÇAS!B:H,7,0),0)/100 -> 0
C40: =IFERROR(VLOOKUP(B40,BANCO_DADOS_PEÇAS!B:C,2,0),"") | G40: =IFERROR(VLOOKUP(B40,BANCO_DADOS_PEÇAS!B:H,6,0),"") | H40: =IFERROR(VLOOKUP(B40,BANCO_DADOS_PEÇAS!B:D,3,0)*(100%+K40)*(100%-J40),"") | I40: =IFERROR((IFERROR(H40+(H40*L40)+(H40*M40),H40)*A40),0) -> 0 | L40: =IFERROR(VLOOKUP(B40,BANCO_DADOS_PEÇAS!B:H,7,0),0)/100 -> 0
C41: =IFERROR(VLOOKUP(B41,BANCO_DADOS_PEÇAS!B:C,2,0),"") | G41: =IFERROR(VLOOKUP(B41,BANCO_DADOS_PEÇAS!B:H,6,0),"") | H41: =IFERROR(VLOOKUP(B41,BANCO_DADOS_PEÇAS!B:D,3,0)*(100%+K41)*(100%-J41),"") | I41: =IFERROR((IFERROR(H41+(H41*L41)+(H41*M41),H41)*A41),0) -> 0 | L41: =IFERROR(VLOOKUP(B41,BANCO_DADOS_PEÇAS!B:H,7,0),0)/100 -> 0
C42: =IFERROR(VLOOKUP(B42,BANCO_DADOS_PEÇAS!B:C,2,0),"") | G42: =IFERROR(VLOOKUP(B42,BANCO_DADOS_PEÇAS!B:H,6,0),"") | H42: =IFERROR(VLOOKUP(B42,BANCO_DADOS_PEÇAS!B:D,3,0)*(100%+K42)*(100%-J42),"") | I42: =IFERROR((IFERROR(H42+(H42*L42)+(H42*M42),H42)*A42),0) -> 0 | L42: =IFERROR(VLOOKUP(B42,BANCO_DADOS_PEÇAS!B:H,7,0),0)/100 -> 0
C43: =IFERROR(VLOOKUP(B43,BANCO_DADOS_PEÇAS!B:C,2,0),"") | G43: =IFERROR(VLOOKUP(B43,BANCO_DADOS_PEÇAS!B:H,6,0),"") | H43: =IFERROR(VLOOKUP(B43,BANCO_DADOS_PEÇAS!B:D,3,0)*(100%+K43)*(100%-J43),"") | I43: =IFERROR((IFERROR(H43+(H43*L43)+(H43*M43),H43)*A43),0) -> 0 | L43: =IFERROR(VLOOKUP(B43,BANCO_DADOS_PEÇAS!B:H,7,0),0)/100 -> 0
... C72: =IFERROR(VLOOKUP(B72,BANCO_DADOS_PEÇAS!B:C,2,0),"") | G72: =IFERROR(VLOOKUP(B72,BANCO_DADOS_PEÇAS!B:H,6,0),"") | H72: =IFERROR(VLOOKUP(B72,BANCO_DADOS_PEÇAS!B:D,3,0)*(100%+K72)*(100%-J72),"") | I72: =IFERROR((IFERROR(H72+(H72*L72)+(H72*M72),H72)*A72),0) -> 0 | L72: =IFERROR(VLOOKUP(B72,BANCO_DADOS_PEÇAS!B:H,7,0),0)/100 -> 0
A73: OBSERVAÇÕES: | G73: TOTAL | H73: =SUM(I32:I72) -> 0

Sheet BANCO_DADOS_PEÇAS
A1: GRU_CODIGO | B1: PRO_CODIGO | C1: DESCRICAO | D1: PRECO_VENDA_CONSUMIDOR | E1: E_PESOBRT | F1: CODIGO_BARRA | G1: E_CLASFIS | H1: E_IPI | AH1: IPI | AI1: ST
A2: 000 | B2: 005 | C2: ESPIG.FIXO FEMEA 1/4X5/16 LATAO | D2: 4.70799 | E2: 0 | F2: SEM GTIN | G2: 74122000 | H2: 3.25 | AH2: 0.05 | AI2: 0
A3: 000 | B3: BBQ-ONE | C3: SMOKER PORTATIL C/ TAMPA | D3: 150.52 | E3: 5 | F3: SEM GTIN | G3: 73218900 | H3: 6.5 | AH3: 0.05 | AI3: 0
A4: 000 | B4: CAR12 | C4: CARRINHO MULTI FUNCAO BASCULANTE C/ VALV DE ESFERA C/PENEIRA | D4: 1579.4 | E4: 0 | F4: SEM GTIN | G4: 87169090 | H4: 3.25 | AH4: 0.05 | AI4: 0
A5: 000 | B5: CARRO002 | C5: REBOQUERG BRUTOS VTAV-PRETA | D5: 21550.718 | E5: 0 | F5: SEM GTIN | G5: 87163900 | H5: 0 | AH5: 0.05 | AI5: 0
A6: 000 | B6: JAR-01 | C6: ESGUICHO P/MANG.C/ESCAMA DE 1/2 LATAO | D6: 24.91 | E6: 5 | F6: SEM GTIN | G6: 84242000 | H6: 3.25 | AH6: 0.05 | AI6: 0
A7: 000 | B7: LAV31 | C7: ENGATE ADAPTADOR 1/4 PARA LAVADORA X R. MACHO 1/4 BSP LATAO | D7: 15.5396 | E7: 0.015 | F7: SEM GTIN | G7: 84811000 | H7: 0 | AH7: 0.05 | AI7: 0
A8: 000 | B8: LAV32 | C8: ADAPTADOR MACHO M22 TUBO 14 X FEMEA 1/4 BSP LATAO | D8: 9.222 | E8: 0.015 | F8: SEM GTIN | G8: 84811000 | H8: 0 | AH8: 0.05 | AI8: 0
A9: 000 | B9: LAV33 | C9: PINO C/ ORING MACHO 1/4 BSP | D9: 4.8866 | E9: 0.015 | F9: SEM GTIN | G9: 84811000 | H9: 0 | AH9: 0.05 | AI9: 0
A10: 000 | B10: LAV34 | C10: PINO CHANFRADO PRENS.P/ GATILHO KARCHER | D10: 6.0102 | E10: 0.015 | F10: SEM GTIN | G10: 73071920 | H10: 3.25 | AH10: 0.05 | AI10: 0
A11: 000 | B11: LAV35 | C11: PINO FEMEA 1/4 | D11: 6.148 | E11: 0.015 | F11: SEM GTIN | G11: 84811000 | H11: 0 | AH11: 0.05 | AI11: 0
A12: 000 | B12: LAV36 | C12: ENGATE ADAPTADOR 1/4 PARA LAVADORA X R. FEMEA 1/4 LATAO | D12: 15.5396 | E12: 0.015 | F12: SEM GTIN | G12: 84811000 | H12: 0 | AH12: 0.05 | AI12: 0
A13: 000 | B13: LAV37 | C13: ADAPTADOR MACHO M22 TUBO 14 X MACHO 1/4 BSP LATAO | D13: 7.208 | E13: 0.015 | F13: SEM GTIN | G13: 84811000 | H13: 0 | AH13: 0.05 | AI13: 0
... A73: 000 | B73: LUB-1989AC | C73: BICO DE AR P/LIMPEZA EM ALUMINIO CINZA | D73: 23.758654 | E73: 0.074 | F73: SEM GTIN | G73: 84242000 | H73: 3.25 | AH73: 0 | AI73: 0
A74: 000 | B74: LUB-1989AP | C74: BICO DE AR P/LIMPEZA EM ALUMINIO PRETO | D74: 18.709 | E74: 0.072 | F74: 7898310838498 | G74: 84242000 | H74: 3.25 | AI74: 0
A75: 000 | B75: LUB-1989AV | C75: BICO DE AR P/LIMPEZA EM ALUMINIO VERMELHA | D75: 18.709 | E75: 0.074 | F75: 7898310838504 | G75: 84242000 | H75: 3.25 | AH75: 0.05 | AI75: 0
A76: 000 | B76: LUB-1989B | C76: BICO DE AR P/LIMPEZA C/BICO DE NYLON | D76: 16.589 | E76: 0.144 | F76: 7898310835688 | G76: 84242000 | H76: 3.25 | AH76: 0.05 | AI76: 0
A77: 000 | B77: LUB-1989C | C77: BICO DE AR P/LIMPEZA C/BICO DE LATAO | D77: 17.278 | E77: 0.158 | F77: 7898310835695 | G77: 84242000 | H77: 3.25 | AH77: 0.05 | AI77: 0
A78: 000 | B78: LUB-1989D | C78: BICO DE AR P/LIMPEZA C/ HASTE 100MM COMPRIMENTO | D78: 25.387 | E78: 0.158 | F78: SEM GTIN | G78: 84242000 | H78: 3.25 | AH78: 0.05 | AI78: 0
A79: 000 | B79: LUB-1989E | C79: BICO DE AR P/LIMPEZA C/ HASTE 250MM COMPRIMENTO | D79: 25.811 | E79: 0.158 | F79: SEM GTIN | G79: 84242000 | H79: 3.25 | AH79: 0.05 | AI79: 0
A80: 000 | B80: LUB-1989NA | C80: BICO DE AR P/LIMPEZA EM NYLON AZUL | D80: 12.19 | E80: 0.074 | F80: SEM GTIN | G80: 84242000 | H80: 3.25 | AH80: 0.05 | AI80: 0
A81: 000 | B81: LUB-1989NP | C81: BICO DE AR P/LIMPEZA EM NYLON PRETO | D81: 12.19 | E81: 0.074 | F81: SEM GTIN | G81: 84242000 | H81: 3.25 | AH81: 0 | AI81: 0
A82: 000 | B82: LUB-1989NV | C82: BICO DE AR P/LIMPEZA EM NYLON VERMELHA | D82: 12.19 | E82: 0.074 | F82: SEM GTIN | G82: 84242000 | H82: 3.25 | AH82: 0 | AI82: 0
A83: 000 | B83: LUB-1990 | C83: PONTA DO BICO DE AR REG ALTA VAZAO BAIXO RUIDO | D83: 9.4234 | E83: 0.144 | F83: SEM GTIN | G83: 84242000 | H83: 3.25 | AH83: 0 | AI83: 0
A84: 000 | B84: LUB-1992AA | C84: PULVERIZADOR PNEUMATICO EM ALUMINIO AZUL | D84: 22.048 | E84: 0.1236 | F84: 7898310838535 | G84: 84242000 | H84: 3.25 | AH84: 0 | AI84: 0
A85: 000 | B85: LUB-1992AC | C85: PULVERIZADOR PNEUM. EM ALUMINIO CINZA | D85: 26.762085 | E85: 0.12 | F85: SEM GTIN | G85: 84242000 | H85: 3.25 | AH85: 0 | AI85: 0
A86: 000 | B86: LUB-1992AP | C86: PULVERIZADOR PNEUMATICO EM ALUMINIO PRETO | D86: 22.048 | E86: 0.12 | F86: 7898310838511 | G86: 84242000 | H86: 3.25 | AH86: 0 | AI86: 0
... A286: 000 | B286: LUB-2040K | C286: ESG. SUPER LONGO P/JARDIM C/ PINO ACOPLAVEL P/ 2040E | D286: 54.7278 | E286: 0.296 | F286: 7898310839914 | G286: 84242000 | H286: 3.25 | AH286: 0.05 | AI286: 0
A287: 000 | B287: LUB-2040L | C287: BICO DE ESGUICHO REG P/LAVADORA ALTA PRESSAO FURO 1MM | D287: 33.92 | F287: SEM GTIN | G287: 84242000 | H287: 3.25 | AH287: 0.05 | AI287: 0
A288: 000 | B288: LUB-2040LP | C288: BICO ESGUICHO REG P/LAVADORA DE ALTA PRESSAO FURO 1.2MM PRO | D288: 33.92 | F288: SEM GTIN | G288: 84242000 | H288: 3.25 | AH288: 0.05 | AI288: 0
A289: 000 | B289: LUB-2050 | C289: ENGATE RAP. HIDRAUL. INDL. DE 1/2 | D289: 53.265 | E289: 0.344 | F289: 7898310837576 | G289: 84811000 | H289: 0 | AH289: 0.05 | AI289: 0
A290: 000 | B290: LUB-2050-1 | C290: PINO DE ENG.HIDR. INDL. 1/2 R. FEMEA | D290: 24.1892 | E290: 0.108 | F290: 7898310837811 | G290: 84811000 | H290: 0 | AH290: 0.05 | AI290: 0
A291: 000 | B291: LUB-2050H | C291: ENGATE RAP. AGRIC. DE 1/2 HIDRAUL. | D291: 43.1526 | E291: 0.304 | F291: 7898310837583 | G291: 84811000 | H291: 0 | AH291: 0.05 | AI291: 0
A292: 000 | B292: LUB-2050H1 | C292: PINO DE ENG.HIDR. R.F. 1/2 AGRICOLA | D292: 23.0338 | E292: 0.088 | F292: 7898310837705 | G292: 84811000 | H292: 0 | AH292: 0.05 | AI292: 0
A293: 000 | B293: LUB-2050HA | C293: ENGATE RAP.HIDRAULICO 1/2 R.MACHO M22 (TRATORES JOHN DERRE) | D293: 96.4176 | E293: 0.554 | F293: 7898310839068 | G293: 84811000 | H293: 0 | AH293: 0.05 | AI293: 0
A294: 000 | B294: LUB-2050HB | C294: ENGATE RAP.HIDRAULICO 1/2 R.MACHO 1/2 (TRATORES NEW HOLAND) | D294: 96.4176 | E294: 0.544 | F294: 7898310839860 | G294: 84811000 | H294: 0 | AH294: 0.05 | AI294: 0
A295: 000 | B295: LUB-2050HC | C295: ENGATE RAP.HIDRAULICO 1/2 R.MACHO 3/4 UNF (TRATORES VALMET) | D295: 96.4176 | E295: 0.548 | F295: 7898310839631 | G295: 84811000 | H295: 0 | AH295: 0.05 | AI295: 0
A296: 000 | B296: LUB-2050HD | C296: ENGATE RAP.HIDRAULICO 1/2 R.MACHO 7/8 UNF (TRATORES MASSEY F | D296: 96.4176 | E296: 0.544 | F296: 7898310839501 | G296: 84811000 | H296: 0 | AH296: 0.05 | AI296: 0
A297: 000 | B297: LUB-2050HE | C297: ENGATE RAP.HIDRAULICO 1/2 R.MACHO 1.1/16 UNF | D297: 109.2754 | E297: 0.544 | F297: SEM GTIN | G297: 84811000 | H297: 0 | AH297: 0.05 | AI297: 0
A298: 000 | B298: LUB-2050HF | C298: ENGATE RAP.HIDRAULICO 1/2 R.MACHO 13/16 UNF | D298: 109.2754 | E298: 0.544 | F298: SEM GTIN | G298: 84811000 | H298: 0 | AH298: 0.05 | AI298: 0
A299: 000 | B299: LUB-2050P | C299: ENGATE E PINO HIDRAULICO 1/2 AP. RF 1/2 | D299: 140.609 | E299: 0.612 | F299: SEM GTIN | G299: 84811000 | H299: 0 | AH299: 0.05 | AI299: 0
A300: 000 | B300: LUB-2050V | C300: KIT DE VEDACAO P/ ENGATE RAP. HIDRAUL. INDL. DE 1/2 | D300: 6.2328 | E300: 0 | F300: SEM GTIN | G300: 40169300 | H300: 0 | AH300: 0.05 | AI300: 0
... A366: 000 | B366: LUB-23R | C366: ESPIGAO C/PORCA GIR. ESQ. P/ACET. MANG. 1/4 | D366: 0 | E366: 0 | F366: SEM GTIN | G366: 73071920 | H366: 3.25 | AH366: 0.05 | AI366: 0
A367: 000 | B367: LUB-23S | C367: ESPIGAO C/PORCA GIR.DIR. P/OX. ESCAMA 1/4 | E367: 0 | F367: SEM GTIN | G367: 73071920 | H367: 3.25 | AH367: 0.05 | AI367: 0
A368: 000 | B368: LUB-24 | C368: ESPIG.FIXO MACHO ROSCA 1/4X1/4 ACO | D368: 2.1518 | E368: 0.015 | F368: 7898310830072 | G368: 73071920 | H368: 3.25 | AH368: 0.05 | AI368: 0
A369: 000 | B369: LUB-24-L | C369: ESPIG.FIXO MACHO ROSCA 1/4 X1/4 LATAO | D369: 4.134 | E369: 0.0172 | F369: 7898310830089 | G369: 74122000 | H369: 3.25 | AH369: 0.05 | AI369: 0
A370: 000 | B370: LUB-24A | C370: ESPIG.FIXO MACHO R. 1/4 X1/8 ACO | D370: 6.307 | E370: 0.012 | F370: 7898310838764 | G370: 73071920 | H370: 3.25 | AH370: 0.05 | AI370: 0
A371: 000 | B371: LUB-24A-L | C371: ESPIG.FIXO MACHO R. 1/4 X1/8 LATAO | D371: 5.989 | E371: 0.0144 | F371: 7898310837682 | G371: 74122000 | H371: 3.25 | AH371: 0.05 | AI371: 0
A372: 000 | B372: LUB-24A1 | C372: ESPIG.FIXO MACHO R. 1/4 X 3/16 ACO | D372: 6.307 | E372: 0.012 | F372: SEM GTIN | G372: 73071920 | H372: 3.25 | AH372: 0 | AI372: 0
A373: 000 | B373: LUB-24A1-L | C373: ESP. FIXO R.MACHO 1/4 X 3/16 LATAO | D373: 5.989 | E373: 0.014 | F373: 7898310838634 | G373: 74122000 | H373: 3.25 | AH373: 0 | AI373: 0
A374: 000 | B374: LUB-24B | C374: ESPIG.FIXO MACHO ROSCA 1/4X5/16 ACO | D374: 2.1518 | E374: 0.0164 | F374: 7898310830096 | G374: 73071920 | H374: 3.25 | AH374: 0.05 | AI374: 0
A375: 000 | B375: LUB-24B-L | C375: ESPIG.FIXO MACHO ROSCA 1/4 X 5/16 LATAO | D375: 4.134 | E375: 0.018 | F375: 7898310830102 | G375: 74122000 | H375: 3.25 | AH375: 0.05 | AI375: 0
A376: 000 | B376: LUB-24C | C376: ESPIG.FIXO MACHO ROSCA 1/4 X3/8 ACO | D376: 2.1518 | E376: 0.0172 | F376: 7898310830119 | G376: 73071920 | H376: 3.25 | AH376: 0.05 | AI376: 0
A377: 000 | B377: LUB-24C-L | C377: ESPIG.FIXO MACHO ROSCA 1/4 X 3/8 LATAO | D377: 4.134 | E377: 0.019 | F377: 7898310830126 | G377: 74122000 | H377: 3.25 | AH377: 0.05 | AI377: 0
A378: 000 | B378: LUB-24D | C378: ESPIG.FIXO MACHO ROSCA 1/4 X1/2 ACO | D378: 2.1518 | E378: 0.02 | F378: 7898310830133 | G378: 73071920 | H378: 3.25 | AH378: 0.05 | AI378: 0
A379: 000 | B379: LUB-24D-L | C379: ESPIG.FIXO MACHO ROSCA 1/4 X1/2 LATAO | D379: 4.134 | E379: 0.023 | F379: 7898310830140 | G379: 74122000 | H379: 3.25 | AH379: 0.05 | AI379: 0
... A518: 000 | B518: LUB-26NGD | C518: ESP. FIXO R.MACHO 1.1/2 X 3/4 LATAO | D518: 48.177 | E518: 0.33 | F518: SEM GTIN | G518: 74122000 | H518: 3.25 | AH518: 0.05 | AI518: 0
A519: 000 | B519: LUB-26NGE | C519: ESP. FIXO R.MACHO 1.1/2 X 1.3/4 LATAO | E519: 0.421 | F519: SEM GTIN | G519: 74122000 | H519: 3.25 | AH519: 0.05 | AI519: 0
A520: 000 | B520: LUB-26NGF | C520: ESP. FIXO R.MACHO 1.1/2 X 1/2 LATAO | E520: 0.421 | F520: SEM GTIN | G520: 74122000 | H520: 3.25 | AH520: 0.05 | AI520: 0
A521: 000 | B521: LUB-26NN | C521: ESP.FIXO MACHO 2 X MANG.1 LATAO | D521: 80.242 | E521: 0.562 | F521: 7898310830607 | G521: 74122000 | H521: 3.25 | AH521: 0.05 | AI521: 0
A522: 000 | B522: LUB-26NN1 | C522: ESP.FIXO R. MACHO 2 X MANG.3/4 | D522: 80.242 | E522: 0.55 | F522: SEM GTIN | G522: 74122000 | H522: 3.25 | AH522: 0.05 | AI522: 0
A523: 000 | B523: LUB-26NN2 | C523: ESPIGAO FIXO R.M. 2.1/2 X 1.1/2 LATAO | D523: 144.84026 | E523: 0.936 | F523: SEM GTIN | G523: 74122000 | H523: 3.25 | AH523: 0.05 | AI523: 0
A524: 000 | B524: LUB-26NNA | C524: ESP.FIXO MACHO 2 X 1.1/4 LATAO | D524: 85.118 | E524: 0.596 | F524: 7898310830614 | G524: 74122000 | H524: 3.25 | AH524: 0.05 | AI524: 0
A525: 000 | B525: LUB-26NNB | C525: ESP.FIXO MACHO 2 X 1.1/2 LATAO | D525: 85.118 | E525: 0.618 | F525: 7898310830621 | G525: 74122000 | H525: 3.25 | AH525: 0.05 | AI525: 0
A526: 000 | B526: LUB-26NNC | C526: ESP. FIXO R.MACHO 2 X 2 LATAO | D526: 99.004 | E526: 0.68 | F526: 7898310830638 | G526: 74122000 | H526: 3.25 | AH526: 0.05 | AI526: 0
A527: 000 | B527: LUB-26NNC1 | C527: ESP. FIXO R.MACHO 2 X 2 LATAO - 70 MM | D527: 0 | E527: 0 | F527: SEM GTIN | G527: 74122000 | H527: 3.25 | AH527: 0.05 | AI527: 0
A528: 000 | B528: LUB-26NNC2 | C528: ESP. FIXO R.MACHO 2P X 3 LATAO | D528: 124.61759 | E528: 0.82 | F528: SEM GTIN | G528: 74122000 | H528: 3.25 | AH528: 0.05 | AI528: 0
A529: 000 | B529: LUB-26NNCS | C529: ESP. FIXO R.M. 1.7/8 X 2 LT ESP. | D529: 0 | E529: 0 | F529: SEM GTIN | G529: 74122000 | H529: 3.25 | AH529: 0.05 | AI529: 0
A530: 000 | B530: LUB-26NND | C530: ESPIGAO FIXO R.M. 2.1/2 X 2.1/2 LATAO | D530: 138.224 | E530: 0.936 | F530: 7898310837590 | G530: 74122000 | H530: 3.25 | AH530: 0.05 | AI530: 0
A531: 000 | B531: LUB-26NND1 | C531: ESPIGAO FIXO R.M. 2.1/2 X 2.1/2 LATAO - 70MM | D531: 0 | E531: 0 | F531: SEM GTIN | G531: 74122000 | H531: 3.25 | AH531: 0.05 | AI531: 0
A532: 000 | B532: LUB-26NND8 | C532: ESPIGAO FIXO R.M. 2.1/2 X 2.1/2 LATAO - NPT 8 FIOS | D532: 0 | E532: 0.936 | F532: SEM GTIN | G532: 74122000 | H532: 3.25 | AH532: 0.05 | AI532: 0
... A689: 000 | B689: LUB-29A-AL | C689: ABRAC. PARA MANG LAVA AUTO 3/4 EM ALUMINIO | D689: 11.024 | E689: 0 | F689: SEM GTIN | G689: 76169900 | H689: 3.25 | AH689: 0 | AI689: 0
A690: 000 | B690: LUB-29AL | C690: ABRAC. PARA MANG LAVA AUTO 1/2 EM ALUMINIO | D690: 9.116 | F690: SEM GTIN | G690: 76169900 | H690: 3.25 | AH690: 0 | AI690: 0
A691: 000 | B691: LUB-2A | C691: LUVA 1/4 FEMEA BSP X 1/8 FEMEA BSP ACO | D691: 3.4662 | E691: 0.016 | F691: 7898310831864 | G691: 73071920 | H691: 3.25 | AH691: 0 | AI691: 0
A692: 000 | B692: LUB-2A-L | C692: LUVA 1/4 FEMEA BSP X 1/8 FEMEA BSP LATAO | D692: 4.452 | E692: 0.02 | F692: 7898310831871 | G692: 74122000 | H692: 3.25 | AH692: 0 | AI692: 0
A693: 000 | B693: LUB-2B | C693: LUVA 1/4 FEMEA BSP X 1/4 FEMEA BSP ACO | D693: 3.4662 | E693: 0.016 | F693: 7898310831888 | G693: 73071920 | H693: 3.25 | AH693: 0.05 | AI693: 0
A694: 000 | B694: LUB-2B-L | C694: LUVA 1/4 FEMEA BSP X 1/4 FEMEA BSP LATAO | D694: 4.452 | E694: 0.018 | F694: 7898310831895 | G694: 74122000 | H694: 3.25 | AH694: 0.05 | AI694: 0
A695: 000 | B695: LUB-2C | C695: LUVA 3/8 FEMEA BSP X 1/8 FEMEA BSP ACO | D695: 5.1198 | E695: 0.03 | F695: 7898310831901 | G695: 73071920 | H695: 3.25 | AH695: 0.05 | AI695: 0
A696: 000 | B696: LUB-2C-L | C696: LUVA 3/8 FEMEA BSP X 1/8 FEMEA BSP LATAO | D696: 4.876 | E696: 0.033 | F696: 7898310831918 | G696: 74122000 | H696: 3.25 | AH696: 0.05 | AI696: 0
A697: 000 | B697: LUB-2D | C697: LUVA 3/8 FEMEA BSP X 1/4 FEMEA BSP ACO | D697: 3.7736 | E697: 0.029 | F697: 7898310831925 | G697: 73071920 | H697: 3.25 | AH697: 0.05 | AI697: 0
A698: 000 | B698: LUB-2D-L | C698: LUVA 3/8 FEMEA BSP X 1/4 FEMEA BSP LATAO | D698: 4.876 | E698: 0.032 | F698: 7898310831932 | G698: 74122000 | H698: 3.25 | AH698: 0.05 | AI698: 0
A699: 000 | B699: LUB-2E | C699: LUVA 3/8 FEMEA BSP X 3/8 FEMEA BSP ACO | D699: 3.7736 | E699: 0.033 | F699: 7898310831949 | G699: 73071920 | H699: 3.25 | AH699: 0.05 | AI699: 0
A700: 000 | B700: LUB-2E-L | C700: LUVA 3/8 FEMEA BSP X 3/8 FEMEA BSP LATAO | D700: 4.876 | E700: 0.0344 | F700: 7898310831956 | G700: 74122000 | H700: 3.25 | AH700: 0.05 | AI700: 0
A701: 000 | B701: LUB-2E1-L | C701: LUVA 3/8 FEMEA X 3/8 FEMEA LT SEXT.ESP. | D701: 0 | E701: 0 | F701: SEM GTIN | G701: 74122000 | H701: 3.25 | AH701: 0.05 | AI701: 0
A702: 000 | B702: LUB-2F | C702: LUVA 1/2 FEMEA BSP X 1/8 FEMEA BSP ACO | D702: 8.586 | E702: 0.053 | F702: 7898310831963 | G702: 73071920 | H702: 3.25 | AH702: 0 | AI702: 0
... A752: 000 | B752: LUB-31B | C752: INFLADOR BOLA PARA COMPRESSOR | D752: 17.634929 | E752: 0.056 | F752: 7898310837903 | G752: 84812019 | H752: 3.25 | AH752: 0.05 | AI752: 0.0968
A753: 000 | B753: LUB-31C | C753: BICO PRENDEDOR P/ENCHER PNEUS C/ACOPL. RAPIDO RF 1/4 | D753: 20.14 | F753: SEM GTIN | G753: 84812019 | H753: 3.25 | AH753: 0.05 | AI753: 0
A754: 000 | B754: LUB-31D | C754: BICO PRENDEDOR P/ENCHER PNEUS C/ACOPL. RAPIDO ESCAMA 5/16 | D754: 20.14 | F754: SEM GTIN | G754: 84812019 | H754: 3.25 | AH754: 0.05 | AI754: 0
A755: 000 | B755: LUB-32 | C755: BICO DUPLO PARA ENCHER PNEUS | D755: 27.510021 | E755: 0.075 | F755: 7898310834117 | G755: 84812019 | H755: 3.25 | AH755: 0.05 | AI755: 0
A756: 000 | B756: LUB-32A | C756: MANOMETRO DE PRESSAO DE 10 / 160 LBS | D756: 67.524597 | E756: 0.19 | F756: 7898310836548 | G756: 90262010 | H756: 0 | AH756: 0.05 | AI756: 0
A757: 000 | B757: LUB-32B | C757: CALIB. RELOGIO C/VALV. P/DESINFLAR 10 A 170 LBS C/BICO DUPLO | D757: 275.10021 | E757: 0.436 | F757: SEM GTIN | G757: 90262010 | H757: 0 | AH757: 0 | AI757: 0
A758: 000 | B758: LUB-32C | C758: MANOMETRO PRESSAO ESC. 20 A 120 LBS S/DUPLA | D758: 40.014576 | E758: 0.07 | F758: 7898310837880 | G758: 90262010 | H758: 0 | AH758: 0.05 | AI758: 0
A759: 000 | B759: LUB-32D | C759: MANOMETRO PRES. DE BOLSO P/CAM. 20 A 120 LBS | D759: 40.014576 | E759: 0.052 | F759: 7898310837910 | G759: 90262010 | H759: 0 | AH759: 0.08 | AI759: 0
A760: 000 | B760: LUB-32E | C760: MANOMETRO PRES. DE BOLSO P/AUTO 4 A 50 LBS | D760: 40.014576 | E760: 0.052 | F760: 7898310837897 | G760: 90262010 | H760: 0 | AH760: 0 | AI760: 0
A761: 000 | B761: LUB-32F | C761: BICO DUPLO AUTO TRAVANTE CURTO 190MM | D761: 34.732278 | E761: 0.075 | F761: SEM GTIN | G761: 84812019 | H761: 3.25 | AH761: 0.05 | AI761: 0
A762: 000 | B762: LUB-32FL | C762: BICO DUPLO AUTO TRAVANTE LONGO 300MM | D762: 41.128 | E762: 0.075 | F762: SEM GTIN | G762: 84818099 | H762: 0 | AH762: 0.05 | AI762: 0
A763: 000 | B763: LUB-32G | C763: BICO DUPLO SEM TRAVA LONGO 300MM | D763: 41.128 | E763: 0.075 | F763: SEM GTIN | G763: 84812019 | H763: 3.25 | AH763: 0.05 | AI763: 0
A764: 000 | B764: LUB-32H | C764: BICO DUPLO ENCHER PNEUS TRATOR DIANTEIRO E TRASEIRO | D764: 30.431646 | E764: 0.075 | F764: SEM GTIN | G764: 84812019 | H764: 3.25 | AH764: 0.05 | AI764: 0
A765: 000 | B765: LUB-32I | C765: CALIBRADOR CAMIN.E TRAT. EXPELIDOR AGUA E DESINF. 0 A 50 LBS | D765: 50.95314 | E765: 0.075 | F765: SEM GTIN | G765: 90262010 | H765: 0 | AH765: 0.05 | AI765: 0
A766: 000 | B766: LUB-32J | C766: CALIB.DE PNEUS C/RELOG. ANALOG. 10 A 170 LBS C/BICO PRESILHA | D766: 243.8 | E766: 0.436 | F766: SEM GTIN | G766: 90262010 | H766: 0 | AH766: 0.05 | AI766: 0
...

Sheet IPI SP
A1: CÓDIGO | B1: DESCRIÇÃO | C1: NCM | D1: IPI
A2: LUB-5D3 | B2: FLANGE DISCO LIXA 4.1/2 ROSCA FEMEA M14 | C2: 39172900 | D2: 0
A3: LUB-5D3 | B3: FLANGE DISCO LIXA 4.1/2 ROSCA FEMEA M14 | C3: 39172900 | D3: 0
A4: LUB-5D4 | B4: FLANGE DISCO LIXA 7 - ROSCA FEMEA M14 | C4: 39172900 | D4: 0
A5: LUB-5D4 | B5: FLANGE DISCO LIXA 7 - ROSCA FEMEA M14 | C5: 39172900 | D5: 0
A6: LUB-5D5 | B6: FLANGE PARA ESMERILHADEIRA 4P E 7P | C6: 39172900 | D6: 0
A7: LUB-5D6 | B7: CHAVE COM PINOS P/ SACAR FLANGE/PORCA ESMERILHADEIRA | C7: 39172900 | D7: 0
A8: LUB-5D6-C | B8: CHAVE COM PINOS P/ SACAR FLANGE/PORCA ESMERILHADEIRA COMBAT | C8: 39172900 | D8: 0
A9: LUB-LAV03 | B9: CAPA-PORCA ESGUICHO ALTA PRESSAO (SUPORTE GICLE) | C9: 39172900 | D9: 0
A10: LUB-LAV03 | B10: CAPA-PORCA ESGUICHO ALTA PRESSAO (SUPORTE GICLE) | C10: 39172900 | D10: 0
A11: LUB-2053 | B11: MANGUEIRA P/ ASPIR. DE PO DE 2 CINZA | C11: 39173100 | D11: 0
A12: LUB-2053 | B12: MANGUEIRA P/ ASPIR. DE PO DE 2 CINZA | C12: 39173100 | D12: 0
A13: LUB-2053A | B13: MANGUEIRA P/ ASPIR. DE PO DE 1.1/2 CINZA | C13: 39173100 | D13: 0
... A328: LUB-FLX29E | B328: MANG.FLEX1/2 550MM TM M F M16 X 1,5 M G M16 X 1,5 CAR MOD | C328: 39173100 | D328: 0.05
B329: MANGUEIRA ESPIRAL C/ 15,00 MTS. C/TERM. | C329: 39173100 | D329: 0.05
A330: LUB-TAP | B330: KIT PROTETOR DE ROSCA M/F P/ENG.AGRIC. 1/2 | C330: 39235000 | D330: 0.05
A331: 004 | B331: . | C331: 40092190 | D331: 0.1
A332: 120 | B332: EXTENS.FLEX.500MM 1/4 X 1/8 MACHO | C332: 40092190 | D332: 0.1
A333: LUB-100 | B333: EXT.FLEX. 1/4 300MM TERM. 1/8 MACHO NPT | C333: 40092190 | D333: 0.1
A334: LUB-100 | B334: EXTENS.FLEX. 1/4 C/ 300MM TERMINAL 1/8 MACHO | C334: 40092190 | D334: 0.1
A335: LUB-100 | B335: EXTENS.FLEX.300MM 1/4 X 1/8 MACHO | C335: 40092190 | D335: 0.1
A336: LUB-1000 | B336: MANG.P/BALDE MAN.DE GRAXA 10 MTS 1 TRAMA SEM TERMINAIS | C336: 40092190 | D336: 0.1
A337: LUB-1000 | B337: MANG.P/BALDE MAN.DE GRAXA 10 MTS 1 TRAMA SEM TERMINAIS | C337: 40092190 | D337: 0.1
A338: LUB-100-1 | B338: EXTENS.FLEX. 1/4 C/ 400MM TERMINAL 1/8 MACHO | C338: 40092190 | D338: 0.1
A339: LUB-100-2 | B339: EXTENSAO FLEXIVEL 470 MM 1/4 NPT X 1/4 NPT | C339: 40092190 | D339: 0.1
A340: LUB-100-3 | B340: EXTENSAO FLEXIVEL 650 MM 1/4 NPT X 1/4 NPT | C340: 40092190 | D340: 0.1
A341: LUB-100-4 | B341: EXTENSAO FLEXIVEL 840 MM 1/4 NPT X 1/8 NPT | C341: 40092190 | D341: 0.1
... A3901: LUB-52Z1 | B3901: ABRACADEIRA DE FITA 127 mm X 146 mm | C3901: 73261900 | D3901: 0
B3902: BUCHA 1/4 MACHO X 1/8 FEMEA LATAO | C3902: 74122000 | D3902: 0.05
A3903: 002 | B3903: ESPIG.FIXO MACHO ROSCA 1 X1/2 LT 50 MM | C3903: 74122000 | D3903: 0.05
A3904: 005 | B3904: ESPIG.FIXO FEMEA 1/4X5/16 LATAO | C3904: 74122000 | D3904: 0.05
A3905: LUB-1014-L | B3905: DES.213001 ADAPT.FILTRO PARKER R.M.1/2 C/LATERAL R.F.3/8 | C3905: 74122000 | D3905: 0.05
A3906: LUB-1014-L | B3906: DES.213001 ADAPT.FILTRO PARKER R.M.7/8 C/LATERAL R.F.3/8 | C3906: 74122000 | D3906: 0.05
A3907: LUB-1030L1 | B3907: ADAPT MANIFOLD M 7/16 UNF X FRM 9/16 UNF LAT | C3907: 74122000 | D3907: 0.05
A3908: LUB-10B | B3908: GICLE ESGUICHO REGULAVEL FURO 0,95 MM | C3908: 74122000 | D3908: 0.05
A3909: LUB-10B | B3909: GICLE ESGUICHO REGULAVEL FURO 0,95 MM | C3909: 74122000 | D3909: 0.05
A3910: LUB-10C | B3910: GICLE ESGUICHO REGULAVEL FURO 1,0 MM | C3910: 74122000 | D3910: 0.05
A3911: LUB-10C | B3911: GICLE ESGUICHO REGULAVEL FURO 1,0 MM | C3911: 74122000 | D3911: 0.05
A3912: LUB-10D | B3912: GICLE ESGUICHO REGULAVEL FURO 1,5 MM | C3912: 74122000 | D3912: 0.05
A3913: LUB-10D | B3913: GICLE ESGUICHO REGULAVEL FURO 1,5 MM | C3913: 74122000 | D3913: 0.05
A3914: LUB-10E | B3914: GICLE ESGUICHO REGULAVEL FURO 2,2 MM | C3914: 74122000 | D3914: 0.05
... A6168: LUB-MIX02 | B6168: MISTURADOR TINTA 3,6 LTS ACOPLAMENTO MANDRIL 3/8 | C6168: 84798210 | D6168: 0
A6169: FAB-00076 | C6169: 84798999 | D6169: 0
A6170: LUB-504A | B6170: ENGRAXADEIRA MANUAL C/ALAV P/ 400GR C/EXT RIG E BICO GRAXA | C6170: 84798999 | D6170: 0
A6171: LUB-504A | B6171: ENGRAXADEIRA MANUAL C/ALAV P/ 400GR C/EXT RIG E BICO GRAXA | C6171: 84798999 | D6171: 0
A6172: LUB-504A-1 | B6172: CABECOTE BOMBA MANUAL C/ALAV P/ 400GR C/EXT RIG E BICO GRAXA | C6172: 84798999 | D6172: 0
A6173: LUB-504A-1 | B6173: CABECOTE BOMBA MANUAL C/ALAV P/ 400GR C/EXT RIG E BICO GRAXA | C6173: 84798999 | D6173: 0
A6174: LUB-504B | B6174: ENGRAXADEIRA MANUAL C/ALAV P/ 400GR C/EXT FLEX E BICO GRAXA | C6174: 84798999 | D6174: 0
A6175: LUB-504B | B6175: ENGRAXADEIRA MANUAL C/ALAV P/ 400GR C/EXT FLEX E BICO GRAXA | C6175: 84798999 | D6175: 0
A6176: LUB-504B-2 | B6176: ENGRAXADEIRA MANUAL C/ALAV P/ 400GR C/EXT FLEX 500 MM E BICO | C6176: 84798999 | D6176: 0
A6177: LUB-C4 | B6177: COMANDO GRAXA C/EXTENSAO FLEXIVEL 300MM E LUB-13 | C6177: 84798999 | D6177: 0
A6178: LUB-C4 | B6178: empresa | C6178: 84798999 | D6178: 0
A6179: LUB-C5 | B6179: COMANDO GRAXA C/EXTENSAO FLEXIVEL 500MM E LUB-13 | C6179: 84798999 | D6179: 0
A6180: LUB-C5 | B6180: COMANDO GRAXA C/EXTENSAO FLEXIVEL 500MM E LUB-13 | C6180: 84798999 | D6180: 0
A6181: LUB-CM | B6181: PISTOLA COMPL. P/APLIC. SEALER CALAFETACAO | C6181: 84798999 | D6181: 0
... A6930: M9 | B6930: . | C6930: 90262010 | D6930: 0

Sheet IPI MG
A1: CÓDIGO | B1: DESCRIÇÃO | C1: NCM | D1: IPI
A2: LUB-5D3 | B2: FLANGE DISCO LIXA 4.1/2 ROSCA FEMEA M14 | C2: 39172900 | D2: 0
A3: LUB-5D4 | B3: FLANGE DISCO LIXA 7 - ROSCA FEMEA M14 | C3: 39172900 | D3: 0
A4: LUB-5D5 | B4: FLANGE PARA ESMERILHADEIRA 4P E 7P | C4: 39172900 | D4: 0
A5: LUB-5D6 | B5: CHAVE COM PINOS P/ SACAR FLANGE/PORCA ESMERILHADEIRA | C5: 39172900 | D5: 0
A6: LUB-5D6-C | B6: CHAVE COM PINOS P/ SACAR FLANGE/PORCA ESMERILHADEIRA COMBAT | C6: 39172900 | D6: 0
A7: LUB-LAV03 | B7: CAPA-PORCA ESGUICHO ALTA PRESSAO (SUPORTE GICLE) | C7: 39172900 | D7: 0
A8: LUB-2053 | B8: MANGUEIRA P/ ASPIR. DE PO DE 2 CINZA | C8: 39173100 | D8: 0
A9: LUB-2053A | B9: MANGUEIRA P/ ASPIR. DE PO DE 1.1/2 CINZA | C9: 39173100 | D9: 0
A10: LUB-2056 | B10: MANGUEIRA DE AR P/COMPRES.1/4 PRETA | C10: 39173100 | D10: 0
A11: LUB-2056A | B11: MANGUEIRA DE AR P/COMPRES.5/16 PRETA | C11: 39173100 | D11: 0
A12: LUB-2056B | B12: MANGUEIRA DE AR P/COMPRES.3/8 PRETA | C12: 39173100 | D12: 0
A13: LUB-2056C | B13: MANGUEIRA DE AGUA P/ALTA PRESSAO 1/2 AZUL | C13: 39173100 | D13: 0
... A256: LUB-FLX29E | B256: MANG.FLEX1/2 550MM TM M F M16 X 1,5 M G M16 X 1,5 CAR MOD | C256: 39173100 | D256: 0.05
B257: MANGUEIRA ESPIRAL C/ 15,00 MTS. C/TERM. | C257: 39173100 | D257: 0.05
A258: LUB-TAP | B258: KIT PROTETOR DE ROSCA M/F P/ENG.AGRIC. 1/2 | C258: 39235000 | D258: 0.05
A259: 004 | B259: . | C259: 40092190 | D259: 0.1
A260: 120 | B260: EXTENS.FLEX.500MM 1/4 X 1/8 MACHO | C260: 40092190 | D260: 0.1
A261: LUB-100 | B261: EXTENS.FLEX. 1/4 C/ 300MM TERMINAL 1/8 MACHO | C261: 40092190 | D261: 0.1
A262: LUB-100 | B262: EXTENS.FLEX.300MM 1/4 X 1/8 MACHO | C262: 40092190 | D262: 0.1
A263: LUB-1000 | B263: MANG.P/BALDE MAN.DE GRAXA 10 MTS 1 TRAMA SEM TERMINAIS | C263: 40092190 | D263: 0.1
A264: LUB-1000 | B264: MANG.P/BALDE MAN.DE GRAXA 10 MTS 1 TRAMA SEM TERMINAIS | C264: 40092190 | D264: 0.1
A265: LUB-100-1 | B265: EXTENS.FLEX. 1/4 C/ 400MM TERMINAL 1/8 MACHO | C265: 40092190 | D265: 0.1
A266: LUB-100-2 | B266: EXTENSAO FLEXIVEL 470 MM 1/4 NPT X 1/4 NPT | C266: 40092190 | D266: 0.1
A267: LUB-100-3 | B267: EXTENSAO FLEXIVEL 650 MM 1/4 NPT X 1/4 NPT | C267: 40092190 | D267: 0.1
A268: LUB-100-4 | B268: EXTENSAO FLEXIVEL 840 MM 1/4 NPT X 1/8 NPT | C268: 40092190 | D268: 0.1
A269: LUB-100-5 | B269: EXTENSAO FLEXIVEL 870 MM 1/4 NPT X 1/8 NPT | C269: 40092190 | D269: 0.1
... A3638: LUB-52Z1 | B3638: ABRACADEIRA DE FITA 127 mm X 146 mm | C3638: 73261900 | D3638: 0
B3639: BUCHA 1/4 MACHO X 1/8 FEMEA LATAO | C3639: 74122000 | D3639: 0.05
A3640: 002 | B3640: ESPIG.FIXO MACHO ROSCA 1 X1/2 LT 50 MM | C3640: 74122000 | D3640: 0.05
A3641: 005 | B3641: ESPIG.FIXO FEMEA 1/4X5/16 LATAO | C3641: 74122000 | D3641: 0.05
A3642: LUB-1014-L | B3642: DES.213001 ADAPT.FILTRO PARKER R.M.1/2 C/LATERAL R.F.3/8 | C3642: 74122000 | D3642: 0.05
A3643: LUB-1014-L | B3643: DES.213001 ADAPT.FILTRO PARKER R.M.7/8 C/LATERAL R.F.3/8 | C3643: 74122000 | D3643: 0.05
A3644: LUB-1030L1 | B3644: ADAPT MANIFOLD M 7/16 UNF X FRM 9/16 UNF LAT | C3644: 74122000 | D3644: 0.05
A3645: LUB-10B | B3645: GICLE ESGUICHO REGULAVEL FURO 0,95 MM | C3645: 74122000 | D3645: 0.05
A3646: LUB-10B | B3646: GICLE ESGUICHO REGULAVEL FURO 0,95 MM | C3646: 74122000 | D3646: 0.05
A3647: LUB-10C | B3647: GICLE ESGUICHO REGULAVEL FURO 1,0 MM | C3647: 74122000 | D3647: 0.05
A3648: LUB-10C | B3648: GICLE ESGUICHO REGULAVEL FURO 1,0 MM | C3648: 74122000 | D3648: 0.05
A3649: LUB-10D | B3649: GICLE ESGUICHO REGULAVEL FURO 1,5 MM | C3649: 74122000 | D3649: 0.05
A3650: LUB-10D | B3650: GICLE ESGUICHO REGULAVEL FURO 1,5 MM | C3650: 74122000 | D3650: 0.05
A3651: LUB-10E | B3651: GICLE ESGUICHO REGULAVEL FURO 2,2 MM | C3651: 74122000 | D3651: 0.05
... A6105: LUB-MIX02 | B6105: MISTURADOR TINTA 3,6 LTS ACOPLAMENTO MANDRIL 3/8 | C6105: 84798210 | D6105: 0
A6106: FAB-00076 | C6106: 84798999 | D6106: 0
A6107: LUB-504A | B6107: ENGRAXADEIRA MANUAL C/ALAV P/ 400GR C/EXT RIG E BICO GRAXA | C6107: 84798999 | D6107: 0
A6108: LUB-504A | B6108: ENGRAXADEIRA MANUAL C/ALAV P/ 400GR C/EXT RIG E BICO GRAXA | C6108: 84798999 | D6108: 0
A6109: LUB-504A-1 | B6109: CABECOTE BOMBA MANUAL C/ALAV P/ 400GR C/EXT RIG E BICO GRAXA | C6109: 84798999 | D6109: 0
A6110: LUB-504A-1 | B6110: CABECOTE BOMBA MANUAL C/ALAV P/ 400GR C/EXT RIG E BICO GRAXA | C6110: 84798999 | D6110: 0
A6111: LUB-504B | B6111: ENGRAXADEIRA MANUAL C/ALAV P/ 400GR C/EXT FLEX E BICO GRAXA | C6111: 84798999 | D6111: 0
A6112: LUB-504B | B6112: ENGRAXADEIRA MANUAL C/ALAV P/ 400GR C/EXT FLEX E BICO GRAXA | C6112: 84798999 | D6112: 0
A6113: LUB-504B-2 | B6113: ENGRAXADEIRA MANUAL C/ALAV P/ 400GR C/EXT FLEX 500 MM E BICO | C6113: 84798999 | D6113: 0
A6114: LUB-C4 | B6114: COMANDO GRAXA C/EXTENSAO FLEXIVEL 300MM E LUB-13 | C6114: 84798999 | D6114: 0
A6115: LUB-C4 | B6115: empresa | C6115: 84798999 | D6115: 0
A6116: LUB-C5 | B6116: COMANDO GRAXA C/EXTENSAO FLEXIVEL 500MM E LUB-13 | C6116: 84798999 | D6116: 0
A6117: LUB-C5 | B6117: COMANDO GRAXA C/EXTENSAO FLEXIVEL 500MM E LUB-13 | C6117: 84798999 | D6117: 0
A6118: LUB-CM | B6118: PISTOLA COMPL. P/APLIC. SEALER CALAFETACAO | C6118: 84798999 | D6118: 0
... A6873: M9 | B6873: . | C6873: 90262010 | D6873: 0

Sheet BANCO_DADOS_CLIENTES
A1: K_COD | B1: K_RAZAO | C1: K_ENDFIS | D1: K_NUMFIS | E1: K_BAIFIS | F1: K_MUNFIS | G1: K_ESTFIS | H1: K_CGCFIS | I1: K_FONECON | J1: K_EMAIL | K1: K_OBSPED | L1: NOME | M1: K_IEFIS | N1: TRANSPORTE
A2: 00000 | B2: DIVERSOS CLIENTES | C2: DIVERSOS CLIENTES | D2: 0 | E2: ...... | G2: PR | H2: 00.000.000/0000-00 | J2: vendas@lubefer.com.br | L2: ADMINISTRACAO | M2: ..................
A3: 00003 | B3: UNIBORRACHAS UNIAO COML BORR. LTDA-MTZ | C3: AV. FLORIANO PEIXOTO, | D3: 3731 | E3: B. BRASIL | F3: UBERLANDIA | G3: MG | H3: 41.688.037/0001-31 | I3: 3432329335 | J3: rafael@uniborrachas.com.br | L3: NETO OLIVEIRA | M3: 702.782.004.0077
A4: 00007 | B4: COML. RODRIGUES NETO TINTAS LTDA-ME | C4: AV. ARGENTINA. 173 | D4: 173 | E4: PQ. PARAISO | F4: ITAPECERICA DA SERRA | G4: SP | H4: 00.833.437/0001-06 | J4: netotinta@gmail.com | L4: CLAUDIO THEODORO | M4: 370098730114
A5: 00009 | B5: CEMA COMERCIO E MANUTENCAO LTDA. | C5: AV. VASCONCELOS COSTA, | D5: 493 | E5: MARTINS | F5: UBERLANDIA | G5: MG | H5: 17.097.973/0001-93 | I5: (34)3236-9318 | J5: cema@hotmail.com; cemacomercio@hotmail.com | L5: NETO OLIVEIRA | M5: 702.052.826.0066
A6: 00010 | B6: LOJAS DOMINICK LTDA. | C6: RUA SANTOS SARAIVA, | D6: 451 | E6: ESTREITO | F6: FLORIANOPOLIS | G6: SC | H6: 83.873.935/0001-00 | I6: (48)2106-2300 | J6: fernando@lojadominik.com.br | K6: TS NORMAL ATE DEZ/2014 | L6: VIG | M6: 250.048.108
A7: 00013 | B7: DECK COMERCIO E SERVICOS LTDA. | C7: RUA MARIA CANDIDA, | D7: 85 | E7: VILA GUILHERME | F7: SAO PAULO | G7: SP | H7: 43.569.649/0001-30 | I7: 3384-8517 | J7: ADEMARDECK@GMAIL.COM | L7: CLAUDIO ANDREANI | M7: 110.331.000.112
A8: 00014 | B8: CARIM FERRAMENTAS EIRELI | C8: RUA BRIGADEIRO GALVAO LOJA 97 | D8: 91 | E8: BARRA FUNDA | F8: SAO PAULO | G8: SP | H8: 62.954.680/0001-30 | I8: 11-3825-0555 | J8: carimferramentas@hotmail.com | K8: SMP 35 DDL /HORARIO DE ALMOCO 11H AS 13H | L8: ROBERTO P. | M8: 108.424.733.116
A9: 00015 | B9: MARCO BOTTEON IND. E COM. LTDA. | C9: AV. EUCLIDES MIRAGAIA, | D9: 2445 | E9: CENTRO | F9: BIRIGUI | G9: SP | H9: 45.381.837/0001-66 | I9: (18)3643-1000 | J9: alexandre@botteon.com.br;botteon@botteon.com.br | L9: ROMUALDO | M9: 214.004.645.113
A10: 00018 | B10: PROPOSTO COM DE EQUIPS E ACESS LTDA | C10: RUA DR. CARVALHO CHAVES, | D10: 534 | E10: PAROLIN | F10: CURITIBA | G10: PR | H10: 81.049.827/0001-91 | I10: (41)3332-2754 | J10: adm3@proposto.com.br; compras@proposto.com.br | K10: SEM ST - CONS FISCAL | L10: M.A. CASTRO | M10: 101.703.92.41
A11: 00025 | B11: PARAFUSOS SAO PAULO LTDA | C11: AV. CALOGERAS, | D11: 1435 | E11: CENTRO | F11: CAMPO GRANDE | G11: MS | H11: 24.658.841/0001-59 | I11: (67) 3382-3268 | J11: compras@parafusossaopaulo.com.br | K11: compras@parafusossaopaulo.com.br | L11: GUGI / DACIO | M11: 28.255.070.4
A12: 00026 | B12: ITAPAR LTDA | C12: RUA BLUMENAU, | D12: 756 | E12: CENTRO | F12: ITAJAI | G12: SC | H12: 01.132.443/0001-07 | I12: (47) 3348-1040 | L12: VIG | M12: 253.245.311
A13: 00028 | B13: PEDRO O. MENDEZ E CIA. LTDA. | C13: RUA ANIBAL VENTURINI | D13: 303 | E13: LUCAS ARAUJO | F13: PASSO FUNDO | G13: RS | H13: 92.147.271/0001-92 | I13: (54) 3313-1774 | J13: pedro.o.mendez@hotmail.com | L13: ADMINISTRACAO | M13: 091.0114285
A14: 00030 | B14: FERBRASA FERRAMENTAS DO BRASIL LTDA | C14: C-03 LOTE 17 LOJA 02 | D14: 0 | E14: CENTRO | F14: TAGUATINGA | G14: DF | H14: 37.072.782/0001-84 | I14: (61)3351-9933 | J14: ferdinando9001@hotmail.com | L14: ADMINISTRACAO | M14: 07.308.940001.75
A15: 00036 | B15: COMERCIO QUINTINO MAQS. E FERRS. LTDA. | C15: AV. AFONSO PENA | D15: 3580 | E15: BRASIL | F15: UBERLANDIA | G15: MG | H15: 25.945.031/0001-46 | I15: 34-3232-1960 | J15: leonardo@quintinoferramentas.com | L15: NETO OLIVEIRA | M15: 702.628.883.0020
A16: 00043 | B16: ANG EQUIPAMENTOS LTDA | C16: AV. JK, | D16: 516 | E16: VILA BRETAS | F16: GOVERNADOR VALADARES | G16: MG | H16: 18.330.373/0001-96 | I16: (33)3279-3200 | J16: karina@angequipamentos.com.br | L16: CWP REPRES | M16: 2771523090075
A17: 00045 | B17: A.C. COMERCIO DE FERRAMENTAS LTDA. | C17: AV. SERAFIM GONCALVES PEREIRA, | D17: 473 | E17: PQ NOVO MUNDO | F17: SAO PAULO | G17: SP | H17: 51.167.369/0001-24 | J17: acferramentas@acferramentas.com.br | K17: MANDAR 2000 SEM ENCARTELAR | L17: ANDERSON CERQUEIRA SILVA | M17: 110.100.036.113
A18: 00046 | B18: ALFREDO PECAS E ACES P AUT LTDA EPP | C18: AV. CAMPOS SALLES, | D18: 132 | E18: CENTRO | F18: SANTOS | G18: SP | H18: 44.981.702/0001-79 | I18: (13) 3232-9445 | J18: alfredobaterias@uol.com.br | K18: TRANSPORTADORA GR EXPRESS | L18: CLAUDIO THEODORO | M18: 633.103.588.114
A19: 00049 | B19: AIR WEST COMPRESSORES LTDA EPP | C19: R FAUSTOLO, | D19: 980 | E19: VILA ROMANA | F19: SAO PAULO | G19: SP | H19: 72.937.188/0001-00 | I19: 11-3865-7182 | J19: vendas@airwestcompressores.com.br | L19: CLAUDIO THEODORO | M19: 113.923.813.113
A20: 00051 | B20: AGROSA MAQUINAS E MOTORES LTDA. | C20: RUA PADRE CASSEMIRO, | D20: 650 | E20: CENTRO | F20: CACERES | G20: MT | H20: 37.511.201/0001-63 | I20: (65)3223-1593 | J20: jiboia_koji@hotmail.com | L20: ARI | M20: 13.143.315.6
A21: 00052 | B21: AGRO OESTE COMERCIAL LTDA | C21: AV. DOS TARUMAS, CX P. 79 | D21: 429 | E21: JD. BOTANICO | F21: SINOP | G21: MT | H21: 15.004.997/0001-25 | I21: (66)3531-2782 | J21: elvio@mfzanini.com.br | K21: CNAE PRINC 4661-3/00 NÃO TEM ST | L21: ARI | M21: 13.113.355.1
A22: 00053 | B22: AGRO FERRAGENS LUIZAO LTDA. | C22: AV. FERNANDO CORREIA DA COSTA, | D22: 1118 | E22: CENTRO | F22: RONDONOPOLIS | G22: MT | H22: 24.774.390/0001-15 | I22: (66)3439-2000 | J22: fiscal@luizao.com.br | K22: ENCARTELADO | L22: PELINSON REPRES | M22: 13.071.742.8
A23: 00055 | B23: ADAMS & CIA LTDA | C23: RUA SAO PAULO, | D23: 2087 | E23: CENTRO | F23: CASCAVEL | G23: PR | H23: 78.799.723/0001-90 | I23: (45)3225.2818 | L23: E.S.PEREIRA/EDSON | M23: 410.08504.65
A24: 00059 | B24: ACARAY COM MANGS CONEXOES HIDR LTDA | C24: AV PRES TANCREDO NEVES | D24: 399 | E24: CENTRO | F24: CASCAVEL | G24: PR | H24: 79.554.168/0001-07 | I24: 4532243735 | J24: financeiro@acaraycascavel.com.br | L24: M.A. CASTRO | M24: 4100119213
A25: 00060 | B25: ABRAMAQ COM ABRASIVOS E MAQ EIRELI | C25: TV HUGO FREITAS | D25: 50 | E25: VILA PORTES | F25: FOZ DO IGUACU | G25: PR | H25: 79.576.237/0001-75 | I25: (45)3528-9500 | J25: abramaqnfe@yahoo.com.br | L25: DALSSASO/MARCO | M25: 42.200.847.07
A26: 00062 | B26: A VITORIOSA EQUIPS P/ LUBRIFICACAO LTDA | C26: AV. GETULIO DE MOURA, | D26: 3558 | E26: PRES. JUSCELINO | F26: MESQUITA | G26: RJ | H26: 73.957.284/0001-82 | I26: (21)2796-6874 | J26: avitoriosaltda@gmail.com; danielerossetto@hotmail.com | K26: SO A VISTA ANTECIPADO | L26: ALBAMAR/NILTON | M26: 85.141.325
A27: 00063 | B27: A MILIMETRICA PARAFUSOS E FERR. LTDA | C27: AV. AZENHA, | D27: 616 | E27: AZENHA | F27: PORTO ALEGRE | G27: RS | H27: 72.265.721/0001-34 | J27: amilimetrica@amilimetrica.com.br | L27: ALFA REPRES. | M27: 096.2350583
A28: 00066 | B28: ANT FERRAMENTAS COML E IMPORT. LTDA | C28: RUA PIRATININGA, | D28: 832 | E28: BRAS | F28: SAO PAULO | G28: SP | H28: 74.671.991/0001-70 | I28: (11)3345-3200 | J28: financeiro@antferramentas.com.br;compras@antferramentas.com.br | L28: ANDERSON CERQUEIRA SILVA | M28: 114.005.696.113
A29: 00067 | B29: A.N.L. PARAFUSOS E FERRAMENTAS LTDA | C29: AV. CRUZEIRO DO SUL, | D29: 2611 | E29: SANTANA | F29: SAO PAULO | G29: SP | H29: 60.985.587/0001-67 | I29: (11)2221-5066 | J29: anl@anl.com.br | L29: ANDERSON CERQUEIRA SILVA | M29: 105.187.243.114
A30: 00070 | B30: AUTO PECAS JOAQUINENSE LTDA EPP | C30: RUA GOIAS , | D30: 1551 | E30: CENTRO | F30: SAO JOAQUIM DA BARRA | G30: SP | H30: 44.258.978/0001-23 | I30: (16)3818-0544 | J30: apjoaquinense@netsite.com.br | L30: VICENTE/VPR | M30: 642.010.844.110
A31: 00072 | B31: AUTO LUB MANUTENCAO E COMERCIO LTDA | C31: RUA CERINA, | D31: 201 | E31: ALTO DOS PINHEIROS | F31: BELO HORIZONTE | G31: MG | H31: 23.885.544/0001-83 | J31: rodrigoautolub@yahoo.com.br | L31: ADMINISTRACAO | M31: 062.569.020.0068
A32: 00075 | B32: PARAFUSOS CAME LTDA - ME | C32: R. COLONIZADOR ENIO PIPINO, 52-53 | D32: 52 | E32: INDUSTRIAL NORTE | F32: SINOP | G32: MT | H32: 05.517.762/0001-83 | I32: 6635312896 | J32: parafusoscame@ig.com.br | L32: ARI | M32: 13.349.411.0
A33: 00085 | B33: ROSELI RODRIGUES MORAES COMERCIO | C33: AV. DUQUE DE CAXIAS, CXPST 1519 | D33: 386 | E33: MARRECAS | F33: FRANCISCO BELTRAO | G33: PR | H33: 81.492.092/0001-76 | J33: arbel@wln.com.br | L33: ADMINISTRACAO | M33: 321.024.092.5
A34: 00088 | B34: ARAGUAIA PECAS E IMPL. AGRIC. LTDA | C34: AV. CONEGO JOAO LIMA, | D34: 34 | E34: ENTRONCAMENTO | F34: ARAGUAINA | G34: TO | H34: 02.399.921/0001-02 | I34: (63) 3415-2020 | J34: apiagril@hotmail.com | L34: RIBEIRO & PIMENTEL | M34: 29.000.575.2
A35: 00092 | B35: ASSISTENCIA MEC HIDRAUL GOIAS LTDA EPP | C35: RUA P 16, 204 | D35: 0 | E35: SETOR FUNCIONARIOS | F35: GOIANIA | G35: GO | H35: 02.665.586/0001-39 | I35: 62-3233.4800 | J35: amhigomatriz@terra.com.br | L35: ENIO SILVA | M35: 10.040.995.4
A36: 00094 | B36: ALPRENA COM. MATERIAL P/ SOLDA LTDA. | C36: AV. PATRICIO LIMA, | D36: 625 | E36: HUMAITA | F36: TUBARAO | G36: SC | H36: 81.390.619/0001-51 | I36: (48) 3622-2233 | L36: VIG | M36: 251.876.330
A37: 00095 | B37: ALMEIDA, ALMEIDA, ALMEIRA E ALMEIDA LTDA | C37: RUA DOS EXPEDICIONARIOS, 668 CX.P. 73 | D37: 73 | E37: CENTRO | F37: OURINHOS | G37: SP | H37: 53.418.257/0001-24 | I37: (14) 3326-1600 | J37: compras2.almeida@gmail.com | L37: ROMUALDO | M37: 495.005.602.110
A38: 00097 | B38: BRUSFER COMERCIO DE FERRAGENS LTDA. | C38: AV. OTTO RENAUX, | D38: 310 | E38: CENTRO | F38: BRUSQUE | G38: SC | H38: 00.442.819/0001-09 | I38: (47)3351-3423 | J38: compras@brusfer.com.br | K38: ST NORMAL ATE DEZ/2014 | L38: VIG | M38: 252.965.418
A39: 00098 | B39: BRUNETTI ABRASIVOS E SOLDA LTDA. | C39: AV. SILVIO AVIDOS, | D39: 221 | E39: SAO SILVANO | F39: COLATINA | G39: ES | H39: 31.755.812/0001-70 | I39: (27)3721-3380 | J39: brunettiabras@hotmail.com | L39: ARISTOTELES - ARI REPR.ES | M39: 081.221.037
A40: 00100 | B40: COMPRESSORES E MAQUINAS LTDA | C40: RUA P 7, QD. P 77 LOTE 03 | D40: 215 | E40: SETOR DOS FUNCIONARI | F40: GOIANIA | G40: GO | H40: 02.374.124/0001-62 | I40: (62)32337198 | J40: atlantecnica@terra.com.br | L40: ENIO SILVA | M40: 10.301.633.3
A41: 00105 | B41: BORRACHAS JUNDIAI LTDA 0001 | C41: R SEIKE SAITO | D41: 685 | E41: VILA LACERDA | F41: JUNDIAI | G41: SP | H41: 64.694.383/0001-28 | I41: 11-4585-6600 | J41: compras@borrachasjundiai.com.br | K41: 02/26 SOMENTE A VISTA | L41: RAFAEL GODOY | M41: 407.143.593.115BOR
A42: 00106 | B42: BORRACHAS DA MOOCA LTDA | C42: RUA BIXIRA, | D42: 40 | E42: MOOCA | F42: SAO PAULO | G42: SP | H42: 48.468.979/0001-53 | I42: (11)2020-1144 | J42: nfe@borrachasdamooca.com.br ;mario.vendas@borrachasdamooca.com.br | K42: SEMPRE MANDAR NF XML PARA AUT ENTREGA | L42: ANDERSON CERQUEIRA SILVA | M42: 110.567.050.111
A43: 00107 | B43: BORRACHAS CAIRES LTDA | C43: RUA MAGARINOS TORRES | D43: 1232 | E43: VILA MARIA | F43: SAO PAULO | G43: SP | H43: 55.385.082/0001-21 | I43: 11-2954-2241 | J43: fiscal@caires.com.br;caires@caires.com.br | K43: 10DDL 2% | L43: ROBERTO P. | M43: 111.410.943.117
A44: 00108 | B44: BORRACHAS ARAGUAIA LTDA (MATRIZ) | C44: AV. CASTELO BRANCO | D44: 11685 | E44: ST. RODOVIARIO | F44: GOIANIA | G44: GO | H44: 01.840.594/0001-01 | I44: (62) 3581-1133 | L44: ENIO SILVA | M44: 10.153.631.3
A45: 00110 | B45: BORMAX CORREIAS E MANG. IND. LTDA | C45: RUA MADRE DE DEUS | D45: 883 | E45: MOOCA | F45: SAO PAULO | G45: SP | H45: 56.075.146/0001-50 | I45: (11)2602-7474 | J45: nfe@bormax.com.br; diego.rejano@bormax.com.br | L45: NOEL BUENO RIBEIRO | M45: 147.297.906.116
A46: 00111 | B46: BORGES CASTRO E CIA LTDA | C46: RUA ISRAEL PINHEIRO, | D46: 142 | E46: ALTO PEREIRA | F46: ITABIRA | G46: MG | H46: 22.502.702/0001-06 | I46: (31)3839-7620 | J46: casadaborracha@cborracha.com.br | L46: CWP REPRES | M46: 317.546.544.0066
A47: 00114 | B47: BISMARK COMERCIAL FERRAGENS LTDA. | C47: AV. PRESIDENTE VARGAS, | D47: 401 | E47: CENTRO | F47: DRACENA | G47: SP | H47: 43.470.608/0001-92 | I47: (18)3821-3295 | J47: compras@grupobismark.com.br | L47: ROMUALDO | M47: 292.012.624.111
A48: 00117 | B48: COMERCIAL DE FERRAGENS FERNANDES LTDA. | C48: AV. IMIRIM, 4242 | D48: 4242 | E48: IMIRIM | F48: SAO PAULO | G48: SP | H48: 62.669.668/0001-83 | I48: 11-3982-2089 | J48: coml.fernandes@globo.com; nfe.fernandes@globo.com | K48: VENDAS SO COM AUTORIZACAO DO VENDEDOR | L48: RAFAEL DUARTE | M48: 108.259.050.113
A49: 00118 | B49: BERGMAN MATERIAIS MANUTENCAO LTDA | C49: R RIO DAS PEDRAS, | D49: 477 | E49: JARDIM DO TREVO | F49: CAMPINAS | G49: SP | H49: 00.156.652/0001-10 | J49: bergman@bergman.com.br | L49: CARLOS AUGUSTO | M49: 244.477.081.112
A50: 00119 | B50: BECO DOS FOGOES PECAS E ACESS LTDA | C50: RUA FIRMIANO PINTO | D50: 58 | E50: BRAS | F50: SAO PAULO | G50: SP | H50: 57.288.482/0001-44 | I50: 22910327 | J50: vendas@becogasmetal.com.br;rodrigo@becogasmetal.com.br | K50: ATENCAO LOCAL DE ENTREGA | L50: ANDERSON CERQUEIRA SILVA | M50: 111.687.003.111
A51: 00120 | B51: BECO COMERCIO DE ACESSORIOS LTDA | C51: RUA XAVANTES, | D51: 137 | E51: AGUA VERDE | F51: BLUMENAU | G51: SC | H51: 76.363.928/0001-00 | I51: (47)32099266 | J51: jairbeco@bol.com.br | K51: SACA FILTRO TAMANHO CORRETO 65X77!!!!!!! | L51: VIG | M51: 250925605
A52: 00122 | B52: BARROS E QUEIROZ LTDA | C52: RUA MARECHAL MALLET, | D52: 840 | E52: CENTRO | F52: AQUIDAUANA | G52: MS | H52: 01.926.393/0001-21 | I52: (67)3241-3326 | J52: compras.queiroz@hotmail.com | L52: GUGI / DACIO | M52: 28.235.214.7
A53: 00124 | B53: BARBOSA E RODRIGUES LTDA | C53: AV LUDOVICO DA RIVA NETO, LT 02-QD 01, N | D53: 2652 | E53: SETOR D | F53: ALTA FLORESTA | G53: MT | H53: 01.424.738/0001-49 | I53: (66)3521-2486 | J53: apanteraf@gmail.com | K53: END DE ENTREGA DIFERENTE. | L53: ARI | M53: 13.022.679.3
A54: 00126 | B54: C.B.A. BORRACHAS E PLASTICOS LTDA | C54: AV. PEREIRA BARRETO, | D54: 2376 | E54: JD. PAULISTANO | F54: SANTO ANDRE | G54: SP | H54: 54.113.238/0001-52 | J54: nfe@cbaborrachas.com.br; administrativo@cbaborrachas.com.br | K54: NAO LIGAR QUANDO FOR A VENDEDORA BARBARA | L54: ROBERTO P. | M54: 626.169.220.119
A55: 00128 | B55: C.L.B. COMERCIO DE EQUIPAM. ASSIS LTDA | C55: AV. ARMANDO SALES DE OLIVEIRA | D55: 858 | E55: VILA XAVIER | F55: ASSIS | G55: SP | H55: 00.517.097/0001-04 | I55: (18)3322-5524 | J55: financeiro@clb.com.br | L55: ROMUALDO | M55: 189.068.222.116
A56: 00129 | B56: VIA PRODUCTS LTDA EPP | C56: AV GUARULHOS, | D56: 1548 | E56: CENTRO | F56: GUARULHOS | G56: SP | H56: 58.508.136/0001-97 | J56: nfe@grupocbv.com;compras@grupocbv.com | L56: ANDERSON CERQUEIRA SILVA | M56: 336.228.500.112
A57: 00130 | B57: CENTERBOR COM. DE BORR. E PLAST. LTDA | C57: AV. PRESIDENTE KENNEDY, | D57: 668 | E57: CIDADE NOVA | F57: INDAIATUBA | G57: SP | H57: 62.100.383/0001-27 | J57: centerbor@centerbor.com.br; luiz@centerbor.com.br | K57: SO ACO - 17/12 BO413 CREDITO | L57: CARLOS AUGUSTO | M57: 353.042.777.117
A58: 00133 | B58: FEPAR PARAFUSOS E FERRAMENTAS LTDA | C58: AVENIDA CALOGERAS, | D58: 1479 | E58: CENTRO | F58: CAMPO GRANDE | G58: MS | H58: 26.850.339/0001-70 | I58: (67) 3383-3104 | J58: feparms@terra.com.br | L58: GUGI / DACIO | M58: 28.267.617.1
A59: 00134 | B59: C.S. FERRAMENTAS LTDA | C59: AV GENERAL CARNEIRO, | D59: 84 | E59: VILA SANTA TEREZINHA | F59: SOROCABA | G59: SP | H59: 72.738.214/0001-70 | I59: (15)2101-1111 | J59: erivelton@csferramentas.com.br | L59: VASCONCELOS SP | M59: 669.267.206.111
A60: 00137 | B60: CADORE BIDOIA E CIA LTDA PRIMAVERA | C60: RUA RIO DE JANEIRO, 1475 | D60: 1475 | E60: CENTRO | F60: PRIMAVERA DO LESTE | G60: MT | H60: 26.552.687/0001-61 | I60: 663498-1313 | J60: nfe@cbagricola.com.br | K60: 11/25 - CLIENTE TEM CREDITO BO 371/2025 | L60: PELINSON REPRES | M60: 131.212.35.4
A61: 00139 | B61: CALEGARI FERRAMENTAS LTDA. | C61: RUA HUMBERTO DE CAMPOS, | D61: 526 | E61: CENTRO | F61: LAGES | G61: SC | H61: 81.326.241/0001-27 | I61: (49)3223-2491 | J61: calegariferramentas@yahoo.com.br | L61: VIG | M61: 251.796.795
A62: 00140 | B62: CANTELLI EQUIP PARA LUBRIFICACAO LTDA | C62: R SAPUCAIA, | D62: 185 | E62: MOOCA | F62: SAO PAULO | G62: SP | H62: 60.987.500/0001-90 | I62: (11)2693-3190 | J62: canthelle@yahoo.com.br | L62: ANDERSON CERQUEIRA SILVA | M62: 105.671.075.110
A63: 00142 | B63: CFQ FERRAMENTAS LTDA | C63: RUA ERNESTO VILELA, | D63: 2676 | E63: BOA VISTA | F63: PONTA GROSSA | G63: PR | H63: 00.472.957/0001-30 | J63: compras@cefeq.com.br;nfe@cefeq.com.br | L63: ADMINISTRACAO | M63: 201.14867.73
A64: 00144 | B64: CASA DA BORRACHA RIBEIROPRETANA LTDA | C64: AV FRANCISCO JUNQUEIRA,460 | D64: 0 | E64: CAMPOS ELIZEOS | F64: RIBEIRAO PRETO | G64: SP | H64: 55.961.809/0001-71 | I64: 16-3625-0826 | J64: casadaborracha.rp@terra.com.br | L64: VICENTE/VPR | M64: 582.032.699.112
A65: 00146 | B65: CASA DA BORRACHA BAURU LTDA -EPP | C65: RUA ARAUJO LEITE, 8-29 | D65: 829 | E65: CENTRO | F65: BAURU | G65: SP | H65: 45.030.715/0001-25 | I65: (14) 32226693 | J65: casadaborrachabauru@gmail.com | L65: ADMINISTRACAO | M65: 209.024.517.110
A66: 00147 | B66: CASA DA BORRACHA CARMELITANA LTDA. | C66: AV. JOAO PINHEIRO | D66: 38 | E66: CENTRO | F66: MONTE CARMELO | G66: MG | H66: 22.031.355/0001-80 | I66: (34)3842-2115 | J66: casadaborrachacarmelitana@yahoo.com.br | L66: NETO OLIVEIRA | M66: 431.512.037.0024
A67: 00148 | B67: CASA DAS FERRAMENTAS LTDA | C67: RUA TUPIS, | D67: 1525 | E67: BARRO PRETO | F67: BELO HORIZONTE | G67: MG | H67: 17.281.460/0001-38 | I67: (31) 3295-3166 | L67: ADMINISTRACAO | M67: 062.005.548.0089
A68: 00151 | B68: CASA DO BORRACHEIRO LTDA PR | C68: RUA DESEMB. WESTPHALEN | D68: 2520 | E68: PAROLIN | F68: CURITIBA | G68: PR | H68: 75.700.799/0001-28 | I68: (41)3332-2332 | J68: cb@casadoborracheiro.com.br | L68: ADMINISTRACAO | M68: 10.131.507.09
A69: 00153 | B69: CASA DO RADIADOR FERRAM. E PARAF.LTDA | C69: RUA MACIEL PINHEIRO, | D69: 430 | E69: CENTRO | F69: JOAO PESSOA | G69: PB | H69: 09.360.942/0001-55 | I69: (83)3222-0569 | J69: carfel@bol.com.br; carfel.eder@gmail.com | K69: CONSULTAR ST FISCAL | L69: KVASCONSELOS | M69: 16.059.994.6
A70: 00155 | B70: CASA DOS PARAFUSOS LTDA (MONTES CL) | C70: AV ARMENIO VELOSO, | D70: 200 | E70: CENTRO | F70: MONTES CLAROS | G70: MG | H70: 16.914.715/0001-90 | I70: (38)3221-0830 | J70: geferramentas2@gmail.com | L70: ADMINISTRACAO | M70: 433.332.246.0057
A71: 00157 | B71: CASA DOS POSTOS COM.SERV.MOTO BOMBA LT | C71: AV. MANCHESTER, | D71: 1940 | E71: JD NOVO MUNDO | F71: GOIANIA | G71: GO | H71: 37.330.081/0001-06 | I71: (62)3206-1329 | J71: compras@casadospostos.com.br | L71: ENIO SILVA | M71: 10.244.203.7
A72: 00160 | B72: CASA EZIO MAT. ELETRICOS LTDA | C72: AV. GAL ATALIBA LEONEL, | D72: 3571 | E72: PARADA INGLESA | F72: SAO PAULO | G72: SP | H72: 96.452.214/0001-78 | I72: (11)2212-5459 | J72: casaezio@uol.com.br | L72: ANDERSON CERQUEIRA SILVA | M72: 113.681.094.116
A73: 00166 | B73: CELIO GROSSI FERRAGENS LTDA (UBA) | C73: AV.COM.JACINTO S.SOUZA LIMA | D73: 553 | E73: CENTRO | F73: UBA | G73: MG | H73: 23.151.087/0001-01 | I73: (32)3531-4612 | J73: andre@celiogrossi.com.br | L73: CWP REPRES | M73: 699.538.704.0040
A74: 00169 | B74: CENTRO COMERCIAL DO AGRICULTOR LTDA | C74: RUA INDIO CARIRI, | D74: 178 | E74: CENTRO | F74: CAMPINA GRANDE | G74: PB | H74: 08.329.237/0001-22 | I74: (83)3321-6623 | L74: LOURIVAL | M74: 16.020.199.3
A75: 00172 | B75: CICAMPO MAQUINAS E FERRAMENTAS LTDA | C75: R GERMANO BRANDES SENIOR, | D75: 284 | E75: CENTRO | F75: TIMBO | G75: SC | H75: 80.479.231/0001-69 | I75: (47)3382-0931 | J75: compras@cicampo.com.br;nfe@cicampo.com.br | K75: SIMPLES NACIONAL | L75: VIG | M75: 251.595.757
A76: 00178 | B76: CODIMA COML DISTR DE MANGUEIRAS LTDA | C76: RUA SENADOR SALGADO FILHO, | D76: 155 | E76: CORAL | F76: LAGES | G76: SC | H76: 81.372.534/0001-40 | I76: (49)3225-3816 | J76: codima@codima.com.br | L76: VIG | M76: 251.827.372
A77: 00179 | B77: COFAL COMERCIO DE FERR. E ACESS. LTDA | C77: RUA OSWALDO CRUZ, | D77: 350 | E77: PTE SAO JOAO | F77: JUNDIAI | G77: SP | H77: 73.098.733/0001-84 | I77: (11)4527-4200 | J77: cofal@cofal.com.br | L77: SR JUNDIAI REPRESENTAÇÕES | M77: 407.178.360.113
A78: 00187 | B78: OESTE MANGUEIRAS LTDA | C78: AV. PARIGOT DE SOUZA, | D78: 270 | E78: JD. PORTO ALEGRE | F78: TOLEDO | G78: PR | H78: 82.603.929/0001-70 | I78: (45)3054-6476 | J78: oestemangueiras@hotmail.com | L78: DALSSASO/MARCO | M78: 41.805.483.22
A79: 00188 | B79: COLOMBO E COLOMBO LTDA | C79: AV. MARECHAL RONDON | D79: 463 | E79: CENTRO | F79: COLIDER | G79: MT | H79: 32.989.568/0001-73 | I79: (66)3541-1140 | J79: willian@colimel.com.br | L79: ARI | M79: 013.043.900.2
A80: 00190 | B80: COMAB COMERCIAL DE ARTEF. DE BORR. LTD | C80: AV. WASHINGTON LUIS, | D80: 495 | E80: CENTRO | F80: DRACENA | G80: SP | H80: 55.486.609/0001-04 | I80: (18)3821-1875 | J80: comab.dracena@terra.com.br | L80: ROMUALDO | M80: 292.016.285.116
A81: 00192 | B81: COMATOL COM. DE MAQ. MOTOSERRAS LTDA | C81: RUA MATOS COSTA, | D81: 658 | E81: CENTRO | F81: PORTO UNIAO | G81: SC | H81: 82.905.142/0001-62 | I81: (42)3522-1948 | J81: comatol@waw.com.br | L81: VIG | M81: 250.407.663
A82: 00200 | B82: CASA DO INDUZIDO LTDA | C82: AV. AUGUSTO FRANCO | D82: 885 | E82: GETULIO VARGAS | F82: ARACAJU | G82: SE | H82: 32.892.242/0001-23 | I82: (79)3211-5892 | L82: ADMINISTRACAO | M82: 27.085.942.0
A83: 00203 | B83: COMERCIAL DEVIDES BOR MAT IND LAV LTDA | C83: RUA CAMPOS SALLES, | D83: 396 | E83: CENTRO | F83: JAU | G83: SP | H83: 48.364.251/0001-81 | I83: (14)3622-2891 | J83: nfe@comercialdevides.com.br; financeiro@comercialdevides.com.br | L83: ROMUALDO | M83: 401.007.058.111
A84: 00207 | B84: FERNANDO NUNES FACHINI | C84: RUA BLUMENAU, | D84: 695 | E84: SAO JOAO | F84: ITAJAI | G84: SC | H84: 78.830.353/0001-06 | I84: 4733480950 | J84: comercial@comercialfachini.com.br | K84: SIMPLES NACINAL | L84: VIG | M84: 251.165.620
A85: 00211 | B85: COMERCIAL ELETRO MECANICA CERVI LTDA | C85: RUA TIRADENTES 219 | D85: 219 | E85: AZAMBUJA | F85: BRUSQUE | G85: SC | H85: 77.910.438/0001-31 | I85: (47) 3351-0009 | J85: jcervi@terra.com.br | L85: VIG | M85: 251.058.140
A86: 00214 | B86: COMERCIAL L. SOARES LTDA | C86: RUA SILVA JARDIM | D86: 504 | E86: VILA MORAES | F86: OURINHOS | G86: SP | H86: 61.025.367/0001-54 | I86: (14)3322.7163 | J86: loucomercial@hotmail.com | L86: ROMUALDO | M86: 495.045.604.116
A87: 00222 | B87: COMERCIAL VEDOVATTI LTDA | C87: RUA FELICIO TARABAY, | D87: 1050 | E87: CENTRO | F87: PRESIDENTE PRUDENTE | G87: SP | H87: 55.348.189/0001-08 | I87: (18)3902-4783 | J87: nfe@comercialvedovati.com.br | L87: ROMUALDO | M87: 562.014.366.116
A88: 00223 | B88: COMERCIAL SAO PAULO LTDA-ME | C88: AV. CAP. OLINTO MANCINI, | D88: 77 | E88: CENTRO | F88: TRES LAGOAS | G88: MS | H88: 04.395.994/0001-43 | I88: (67)3521-3021 | J88: comercialsaopaulo.3@gmail.com | K88: SCI OK - 03/2024 | L88: ADMINISTRACAO | M88: 28.317.611.3
A89: 00226 | B89: COMERCIO DE MAQUINAS ZOPPELLO LTDA | C89: AV DOM HELDER CAMERA | D89: 808 | E89: PENHA | F89: SAO PAULO | G89: SP | H89: 63.054.993/0001-02 | J89: zoppello@zipmail.com.br | L89: ANDERSON CERQUEIRA SILVA | M89: 109.038.916.118
A90: 00233 | B90: CEOLIN COMPRESSORES LTDA. | C90: AV.DES.MARIO DA SILVA NUNES LT35 QD09 | D90: 148 | E90: JD. LIMOEIRO | F90: SERRA | G90: ES | H90: 36.363.356/0001-37 | I90: (27)3228-0088 | J90: fiscal@ceolincompressores.com.br | K90: REPRES N VISITA. | L90: ARISTOTELES - ARI REPR.ES | M90: 081.483.16.3
A91: 00234 | B91: COMPRESSUL COMPRESSORES LTDA | C91: RUA CLOTARIO PORTUGAL, | D91: 1285 | E91: SAO BERNARDO | F91: UNIAO DA VITORIA | G91: PR | H91: 78.429.222/0001-11 | I91: (42)3522-2832 | J91: adriano@compressul.com.br; jeane@compressul.com.br; | K91: JEANE | L91: ADMINISTRACAO | M91: 3010249596
A92: 00235 | B92: COMPRIMIR COMERCIAL LTDA | C92: AV. JOSE CLETO, | D92: 700 | E92: SANTA CRUZ | F92: BELO HORIZONTE | G92: MG | H92: 71.421.838/0001-05 | I92: (31) 3424.2690 | L92: CWP REPRES | M92: 062.865.601.0041
A93: 00237 | B93: CONECTUDO PECAS E CONEXOES LTDA. | C93: RUA SAO CRISTOVAO, | D93: 746 | E93: SAO CRISTOVAO | F93: RIO DE JANEIRO | G93: RJ | H93: 28.323.350/0001-08 | I93: (21)2103-2934 | J93: gilma@conectudo.com.br; marcos@conectudo.com.br | K93: SO COMPRA EM LATAO | L93: ALBAMAR/NILTON | M93: 83.168.757
A94: 00238 | B94: CONTAGEM COMPRESSORES MAQ E EQUIPS LTDA | C94: ROD. BR 381, | D94: 3 | E94: PQ. RIACHO DAS PEDRA | F94: CONTAGEM | G94: MG | H94: 01.155.425/0001-32 | I94: (31)3396-3305 | J94: contagemcompressores@ig.com.br | L94: CWP REPRES | M94: 186.967.517.0002
A95: 00240 | B95: COPAFER COMERCIAL LTDA | C95: AV DOS ESTADOS | D95: 4555 | E95: SANTA TEREZINHA | F95: SANTO ANDRE | G95: SP | H95: 55.728.224/0001-06 | J95: natalia@copafer.com.br | K95: AGENDAR ENTREGA WHATS | L95: ADMINISTRACAO | M95: 626.179.235.119
A96: 00242 | B96: CORDEIRO MAQUINAS E FERRAMENTAS LTDA | C96: RUA ANUAR DEQUECH GALPAO 10 E 12 | D96: 272 | E96: IPORANGA | F96: SOROCABA | G96: SP | H96: 71.449.201/0001-19 | I96: (15)3229-6300 | J96: nfe@cordeiromaquinas.com.br;ingrid.francini@cordeiromaquinas.com.br; | K96: ATENTAR AOS PRECOS ALGUNS SAO DIFERENTES | L96: GIOVANI SILVA REPRESENTAÇ | M96: 669.025.008.110
A97: 00246 | B97: CORETUL COMERCIO E REPRES. TUPA LTDA | C97: RUA CAETES | D97: 950 | E97: CENTRO | F97: TUPA | G97: SP | H97: 44.570.513/0001-03 | I97: (14)3496-1839 | L97: ROMUALDO | M97: 697.012.004.116
A98: 00250 | B98: CUSTODIO COMPRESSORES E BOMBAS LTDA | C98: AV SAO PAULO, 45 | D98: 45 | E98: VILA ARISTARCO | F98: PRESIDENTE PRUDENTE | G98: SP | H98: 57.959.371/0001-12 | I98: 1832229466 | J98: custodio.compressores@gmail.com | L98: ADMINISTRACAO | M98: 562.081.036.118
A99: 00251 | B99: D.M.D. COMERCIAL LTDA. | C99: RUA SILVA BUENO, | D99: 92 | E99: IPIRANGA | F99: SAO PAULO | G99: SP | H99: 00.932.893/0001-03 | I99: (11)2068-9000 | J99: nfe@dmdcomercial.com.br | L99: ROBERTO P. | M99: 114.544.755.110
A100: 00252 | B100: DANI RETENTORES E CONEXOES LTDA. | C100: RUA CAETANO PINTO | D100: 671 | E100: BRAS | F100: SAO PAULO | G100: SP | H100: 43.720.556/0001-65 | I100: 11-32072165 | J100: daniconexoes1@uol.com.br | L100: ANDERSON CERQUEIRA SILVA | M100: 109.029.313.113
...
